ovh/__init__.py
ovh/client.py
ovh/config.py
ovh/consumer_key.py
ovh/exceptions.py
ovh/oauth2.py
ovh-1.2.0.dist-info/LICENSE
ovh-1.2.0.dist-info/METADATA
ovh-1.2.0.dist-info/WHEEL
ovh-1.2.0.dist-info/top_level.txt
ovh-1.2.0.dist-info/RECORD
