Metadata-Version: 2.1
Name: ovh
Version: 1.2.0
Summary: "Official module to perform HTTP requests to the OVHcloud APIs"
Home-page: https://api.ovh.com
Author: OVHcloud team - Romain Beuque
Author-email: api@ml.ovh.net
License: BSD
Project-URL: Changelog, https://github.com/ovh/python-ovh/blob/master/CHANGELOG.md
Project-URL: Repository, https://github.com/ovh/python-ovh.git
Project-URL: Issues, https://github.com/ovh/python-ovh/issues
Keywords: ovh,sdk,rest,ovhcloud
Classifier: License :: OSI Approved :: BSD License
Classifier: Development Status :: 5 - Production/Stable
Classifier: Intended Audience :: Developers
Classifier: Operating System :: OS Independent
Classifier: Programming Language :: Python
Classifier: Programming Language :: Python :: 3
Classifier: Programming Language :: Python :: 3.7
Classifier: Programming Language :: Python :: 3.8
Classifier: Programming Language :: Python :: 3.9
Classifier: Programming Language :: Python :: 3.10
Classifier: Programming Language :: Python :: 3.11
Classifier: Programming Language :: Python :: 3.12
Classifier: Topic :: Software Development :: Libraries :: Python Modules
Classifier: Topic :: System :: Archiving :: Packaging
License-File: LICENSE
Requires-Dist: requests>=2.31.0
Requires-Dist: requests-oauthlib>=2.0.0
Provides-Extra: dev
Requires-Dist: Sphinx==1.2.2; extra == "dev"
Requires-Dist: black; extra == "dev"
Requires-Dist: coverage~=7.2.2; extra == "dev"
Requires-Dist: flake8; extra == "dev"
Requires-Dist: isort; extra == "dev"
Requires-Dist: pytest~=7.2.2; extra == "dev"
Requires-Dist: pytest-cov==4.0.0; extra == "dev"
Requires-Dist: setuptools>=30.3.0; extra == "dev"
Requires-Dist: wheel; extra == "dev"
